bamboo/__init__.py
bamboo/error.py
bamboo/types.py
bamboo/utils.py
bamboo/writer.py
bamboo/backend/__init__.py
bamboo/backend/_brightfield.py
bamboo/cli/__init__.py
bamboo/cli/brightfield/__init__.py
bamboo/cli/brightfield/nn.py
bamboo/cli/brightfield/tile.py
bamboo/cli/brightfield/utils.py
bamboo/image/__init__.py
bamboo/image/_brightfield.py
bamboo/models/__init__.py
bamboo/models/_manager.py
bamboo/models/_semantic.py
bamboo/models/zoo/__init__.py
bamboo/models/zoo/_grandqc.py
bamboo/tile/__init__.py
bamboo/tile/_base.py
bamboo/tile/_generic.py
bamboo/tile/_iter.py
bamboo/tile/_rgb.py
bamboo/tools/__init__.py
bamboo/tools/_resize.py
bamboo-0.0.4.dist-info/METADATA
bamboo-0.0.4.dist-info/WHEEL
bamboo-0.0.4.dist-info/entry_points.txt
bamboo-0.0.4.dist-info/licenses/LICENSE.md
bamboo-0.0.4.dist-info/RECORD
