Metadata-Version: 2.4
Name: bamboo
Version: 0.0.4
Summary: Flexible image analysis for the spatial biology era
Author-email: Tom Ouellette <t.ouellette@mail.utoronto.ca>
License-File: LICENSE.md
Requires-Python: >=3.12
Requires-Dist: anci>=0.1.2
Requires-Dist: imagecodecs>=2023.3.16
Requires-Dist: joblib>=1.5.1
Requires-Dist: matplotlib>=3.10.5
Requires-Dist: numpy>=1.24.4
Requires-Dist: pillow>=10.4.0
Requires-Dist: tifffile>=2023.7.10
Requires-Dist: torch>=2.0
Requires-Dist: tqdm>=4.67.1
Requires-Dist: zarr>=3.0.1
Provides-Extra: openslide
Requires-Dist: openslide-bin; extra == 'openslide'
Requires-Dist: openslide-python>=1.4.0; extra == 'openslide'
Provides-Extra: tests
Requires-Dist: pytest; extra == 'tests'
